perfectpizza/__init__.py
perfectpizza/cli.py
perfectpizza/dom.py
perfectpizza/mutations.py
perfectpizza/parser.py
perfectpizza/py.typed
perfectpizza/selectors.py
perfectpizza/utils.py
perfectpizza-1.0.0.dist-info/licenses/LICENSE
perfectpizza-1.0.0.dist-info/METADATA
perfectpizza-1.0.0.dist-info/WHEEL
perfectpizza-1.0.0.dist-info/entry_points.txt
perfectpizza-1.0.0.dist-info/top_level.txt
perfectpizza-1.0.0.dist-info/RECORD
