Metadata-Version: 2.4
Name: perfectpizza
Version: 1.0.0
Summary: A blazing-fast, functional HTML parser for Python
Home-page: https://github.com/Harrygithubportfolio/PerfectPizza
Author: Harry Graham
Author-email: Harry Graham <harry@actionsmartai.com>
Maintainer-email: Harry Graham <harry@actionsmartai.com>
License: MIT License
Project-URL: Homepage, https://github.com/Harrygithubportfolio/PerfectPizza
Project-URL: Documentation, https://github.com/Harrygithubportfolio/PerfectPizza/wiki
Project-URL: Repository, https://github.com/Harrygithubportfolio/PerfectPizza.git
Project-URL: Bug Tracker, https://github.com/Harrygithubportfolio/PerfectPizza/issues
Project-URL: Changelog, https://github.com/Harrygithubportfolio/PerfectPizza/blob/main/CHANGELOG.md
Keywords: html,parser,css,selectors,web scraping,dom,beautifulsoup,functional
Platform: any
Classifier: Development Status :: 4 - Beta
Classifier: Intended Audience :: Developers
Classifier: Topic :: Internet :: WWW/HTTP
Classifier: Topic :: Software Development :: Libraries :: Python Modules
Classifier: Topic :: Text Processing :: Markup :: HTML
Classifier: License :: OSI Approved :: MIT License
Classifier: Programming Language :: Python :: 3
Classifier: Programming Language :: Python :: 3.8
Classifier: Programming Language :: Python :: 3.9
Classifier: Programming Language :: Python :: 3.10
Classifier: Programming Language :: Python :: 3.11
Classifier: Programming Language :: Python :: 3.12
Classifier: Operating System :: OS Independent
Requires-Python: >=3.8
License-File: LICENSE
Provides-Extra: dev
Requires-Dist: pytest>=6.0; extra == "dev"
Requires-Dist: pytest-cov>=2.0; extra == "dev"
Requires-Dist: black>=21.0; extra == "dev"
Requires-Dist: flake8>=3.8; extra == "dev"
Requires-Dist: mypy>=0.900; extra == "dev"
Requires-Dist: build>=0.7; extra == "dev"
Requires-Dist: twine>=3.4; extra == "dev"
Provides-Extra: pandas
Requires-Dist: pandas>=1.0; extra == "pandas"
Provides-Extra: requests
Requires-Dist: requests>=2.25; extra == "requests"
Provides-Extra: performance
Requires-Dist: lxml>=4.6; extra == "performance"
Provides-Extra: all
Requires-Dist: pandas>=1.0; extra == "all"
Requires-Dist: requests>=2.25; extra == "all"
Dynamic: author
Dynamic: home-page
Dynamic: license-file
Dynamic: platform
Dynamic: requires-python
